CHANGES.txt
LICENSE.txt
bootstrap.py
buildout.cfg
setup.py
src/lovely/__init__.py
src/lovely.session.egg-info/PKG-INFO
src/lovely.session.egg-info/SOURCES.txt
src/lovely.session.egg-info/dependency_links.txt
src/lovely.session.egg-info/namespace_packages.txt
src/lovely.session.egg-info/not-zip-safe
src/lovely.session.egg-info/requires.txt
src/lovely.session.egg-info/top_level.txt
src/lovely/session/README.txt
src/lovely/session/__init__.py
src/lovely/session/configure.zcml
src/lovely/session/interfaces.py
src/lovely/session/lovely.session-configure.zcml
src/lovely/session/memcached.py
src/lovely/session/tests.py