Metadata-Version: 1.0
Name: lovely.session
Version: 0.2.1
Summary: memcache-based session storage
Home-page: http://pypi.python.org/pypi/lovely.session
Author: Lovely Systems GmbH
Author-email: office@lovelysystems.com
License: ZPL 2.1
Keywords: zope3 session memcache
Platform: UNKNOWN
Classifier: Development Status :: 4 - Beta
Classifier: Environment :: Web Environment
Classifier: Intended Audience :: Developers
Classifier: License :: OSI Approved :: Zope Public License
Classifier: Programming Language :: Python
Classifier: Natural Language :: English
Classifier: Operating System :: OS Independent
Classifier: Topic :: Internet :: WWW/HTTP
Classifier: Topic :: Software Development :: Libraries :: Python Modules
Classifier: Framework :: Zope3
